simpleM/1234.txt
simpleM/__init__.py
simpleM/display.py
simpleM/data/aa.txt
simpleM/data/zxc.txt
simpleM-0.1.55.data/data/.simpleM/b.txt
simpleM-0.1.55.dist-info/METADATA
simpleM-0.1.55.dist-info/WHEEL
simpleM-0.1.55.dist-info/entry_points.txt
simpleM-0.1.55.dist-info/top_level.txt
simpleM-0.1.55.dist-info/RECORD
